{"cameraMode":{"drawMode":0,"name":"Shaded","section":"Shading Mode"},"sceneLighting":true,"audioPlay":false,"sceneViewState":{"m_AlwaysRefresh":false,"showFog":true,"showSkybox":true,"showFlares":true,"showImageEffects":true,"showParticleSystems":true,"showVisualEffectGraphs":true,"m_FxEnabled":true},"in2DMode":false,"pivot":{"x":84.75497436523438,"y":2.2893638610839845,"z":59.778194427490237},"rotation":{"x":0.609831690788269,"y":-0.03772449493408203,"z":0.02915068529546261,"w":0.7911237478256226},"size":88.56614685058594,"orthographic":false}